{"root" : [
    {
        "person_id" : 7727802,
        "last_name" : "Smith",
        "address" : [{
            "house_number": "1B",
            "house_name": "Mill House",
    
            "street_name" : "Argyle",
            "street_type": "Street",
    
            "city" : "Hyde Werneth Ward",
            "governing_district" : "Greater Manchester",
    
            "country": "United Kingdom"
        }],
        "phone" : [
            "07849266425"
        ],
        "email" : [
            "wild.at.hotmail.com"
        ]
    }
    
]}